{"v":4,"entries":{"docs--docs":{"id":"docs--docs","title":"Docs","name":"Docs","importPath":"./stories/Docs.mdx","storiesImports":[],"type":"docs","tags":["unattached-mdx","docs"]},"scrollmenu-simple--simple":{"type":"story","id":"scrollmenu-simple--simple","name":"Simple","title":"ScrollMenu/Simple","importPath":"./stories/0_Simple/Simple.stories.tsx","tags":["story"]},"scrollmenu-simple--test":{"type":"story","id":"scrollmenu-simple--test","name":"Test","title":"ScrollMenu/Simple","importPath":"./stories/0_Simple/Simple.stories.tsx","tags":["story"]},"scrollmenu-vertical--vertical":{"type":"story","id":"scrollmenu-vertical--vertical","name":"Vertical","title":"ScrollMenu/Vertical","importPath":"./stories/1_Vertical/Vertical.stories.tsx","tags":["story"]},"scrollmenu-vertical--test":{"type":"story","id":"scrollmenu-vertical--test","name":"Test","title":"ScrollMenu/Vertical","importPath":"./stories/1_Vertical/Vertical.stories.tsx","tags":["story"]},"scrollmenu-bottomarrows--bottom-arrows":{"type":"story","id":"scrollmenu-bottomarrows--bottom-arrows","name":"Bottom Arrows","title":"ScrollMenu/BottomArrows","importPath":"./stories/BottomArrows/BottomArrows.stories.tsx","tags":["story"]},"scrollmenu-bottomarrows--test":{"type":"story","id":"scrollmenu-bottomarrows--test","name":"Test","title":"ScrollMenu/BottomArrows","importPath":"./stories/BottomArrows/BottomArrows.stories.tsx","tags":["story"]},"scrollmenu-mousedrag--mouse-drag":{"type":"story","id":"scrollmenu-mousedrag--mouse-drag","name":"Mouse Drag","title":"ScrollMenu/MouseDrag","importPath":"./stories/MouseDrag/MouseDrag.stories.tsx","tags":["story"]},"scrollmenu-mousedrag--test":{"type":"story","id":"scrollmenu-mousedrag--test","name":"Test","title":"ScrollMenu/MouseDrag","importPath":"./stories/MouseDrag/MouseDrag.stories.tsx","tags":["story"]},"scrollmenu-mousedrag--test-drag":{"type":"story","id":"scrollmenu-mousedrag--test-drag","name":"Test Drag","title":"ScrollMenu/MouseDrag","importPath":"./stories/MouseDrag/MouseDrag.stories.tsx","tags":["play-fn","story"]}}}
